README.md
requirements.txt
setup.py
ko_notification_utils/__init__.py
ko_notification_utils/ding_talk.py
ko_notification_utils/email_smtp.py
ko_notification_utils/response.py
ko_notification_utils/work_weixin.py
ko_notification_utils.egg-info/PKG-INFO
ko_notification_utils.egg-info/SOURCES.txt
ko_notification_utils.egg-info/dependency_links.txt
ko_notification_utils.egg-info/top_level.txt