Metadata-Version: 1.1
Name: ko-notification-utils
Version: 0.0.13
Summary: kubeOperator notification util
Home-page: https://kubeoperator.io/
Author: kubeOperator team
Author-email: support@fit2cloud.com
License: MIT Licence
Keywords: kubeOperator,DingTalk,WeiChat,Email
Platform: any
Classifier: Development Status :: 5 - Production/Stable
Classifier: Intended Audience :: Developers
Classifier: License :: OSI Approved :: MIT License
Classifier: Operating System :: OS Independent
Classifier: Programming Language :: Python
Classifier: Programming Language :: Python :: 3.6
